{
  "confusion": {
    "empty_and_identity": 5161,
    "empty_and_nonidentity": 0,
    "nonempty_and_identity": 0,
    "nonempty_and_nonidentity": 244839
  },
  "distinct_reduced_shadows": 1563,
  "elapsed_seconds": 76.04802107810974,
  "empty_shadow_count": 5161,
  "end": 88000000,
  "expected_full_identity_count": 2468088,
  "final_parity_distribution": [
    [
      "000",
      250000
    ]
  ],
  "identity_count": 5161,
  "mismatch_count": 0,
  "mismatch_examples": [],
  "mode": "shadow-normal-form-profile",
  "product_order": "R(w[0]) * ... * R(w[12]) * R(x)",
  "reduced_length_distribution": [
    [
      0,
      5161
    ],
    [
      2,
      34377
    ],
    [
      4,
      73105
    ],
    [
      6,
      93891
    ],
    [
      8,
      43466
    ]
  ],
  "reused_existing_checkpoint": false,
  "scanned": 250000,
  "schema_version": 1,
  "start": 87750000,
  "top_reduced_shadows": []
}
