{
  "available_floor_mib": 12000,
  "description": "Serial guarded AP16DJ batch build plan",
  "emitted_before_build": false,
  "filters": {
    "max_targets": null,
    "module_contains": [],
    "target_index": [],
    "target_kind": [
      "batch_root"
    ]
  },
  "generation_report": "scripts/generated/phase6z6k8ap16du9gh_compact_hcover_batch_generation.json",
  "phase": "Phase 6Z.6K.8AP.16DJ",
  "results": [
    {
      "available_floor_mib": 12000.0,
      "command": [
        "bash",
        "-lc",
        "export LEAN_NUM_THREADS=1; export LAKE_JOBS=1; timeout 600s lake build Cuboctahedron.Generated.Translation.TwoSource.SupportFamilies.ImpactSubcubeWalshSymbolicCompactDenomDU9GHBatchSmoke"
      ],
      "elapsed_seconds": 2.512063265006873,
      "exit_code": 0,
      "killed_reason": null,
      "kind": "batch_root",
      "max_tree_rss_kib": 4090100,
      "max_tree_rss_mib": 3994.23828125,
      "min_available_seen_kib": 47194044,
      "min_available_seen_mib": 46087.93359375,
      "rss_cap_mib": 4500.0,
      "target": "Cuboctahedron.Generated.Translation.TwoSource.SupportFamilies.ImpactSubcubeWalshSymbolicCompactDenomDU9GHBatchSmoke",
      "target_json": "/tmp/ap16dj_du9gh_serial_guarded/batch_root/000_ImpactSubcubeWalshSymbolicCompactDenomDU9GHBatchSmoke.json"
    }
  ],
  "rss_cap_mib": 4500,
  "status": "passed",
  "target_count": 1,
  "targets": [
    {
      "kind": "batch_root",
      "module": "Cuboctahedron.Generated.Translation.TwoSource.SupportFamilies.ImpactSubcubeWalshSymbolicCompactDenomDU9GHBatchSmoke"
    }
  ],
  "timeout_seconds": 600,
  "trusted_as_final_generated_coverage": false
}
